saltysplits/__init__.py
saltysplits/annotations.py
saltysplits/constants.py
saltysplits/enums.py
saltysplits/main.py
saltysplits/models.py
saltysplits/py.typed
saltysplits/streamlit.py
saltysplits-1.1.4.dist-info/METADATA
saltysplits-1.1.4.dist-info/WHEEL
saltysplits-1.1.4.dist-info/licenses/LICENSE
saltysplits-1.1.4.dist-info/RECORD
