Metadata-Version: 2.4
Name: saltysplits
Version: 1.1.4
Summary: Toolset for modeling of LiveSplit files and analysis of the speedrunning data within
Project-URL: homepage, https://saltysplits.com
Project-URL: repository, https://github.com/jaspersiebring/saltysplits
Project-URL: GitHub, https://github.com/jaspersiebring/saltysplits.git
Project-URL: Streamlit, https://streamlit.saltysplits.com
Author-email: Jasper <j.siebring92@gmail.com>
License-File: LICENSE
Keywords: gaming,livesplit,pydantic,speedrunning,xml
Requires-Python: >=3.12
Requires-Dist: packaging>=24.2
Requires-Dist: pandas>=2.2.3
Requires-Dist: pillow>=11.2.1
Requires-Dist: pydantic-xml[lxml]>=2.15.0
Provides-Extra: streamlit
Requires-Dist: streamlit>=1.44.1; extra == 'streamlit'
